visip/__init__.py
visip/action/__init__.py
visip/action/action_factory.py
visip/action/constructor.py
visip/action/converter.py
visip/action/math.py
visip/action/slots.py
visip/action/std.py
visip/action/wrapped.py
visip/code/__init__.py
visip/code/decorators.py
visip/code/dummy.py
visip/code/formating.py
visip/code/operator_functions.py
visip/code/representer.py
visip/code/unwrap.py
visip/dev/__init__.py
visip/dev/action_instance.py
visip/dev/action_workflow.py
visip/dev/base.py
visip/dev/dag_view.py
visip/dev/data.py
visip/dev/dfs.py
visip/dev/dtype.py
visip/dev/evaluation.py
visip/dev/exceptions.py
visip/dev/extract_signature.py
visip/dev/meta.py
visip/dev/mj_api.py
visip/dev/module.py
visip/dev/parameters.py
visip/dev/task.py
visip/dev/task_result.py
visip/dev/tools.py
visip/dev/type_inspector.py
visip/eval/cache.py
visip_gui/README.md
visip_gui/VISIP.py
visip_gui/__init__.py
visip_gui/config/config_data.py
visip_gui/dagviz/__init__.py
visip_gui/dagviz/abstract.py
visip_gui/dagviz/dagre.py
visip_gui/dagviz/istyle.py
visip_gui/dagviz/py.typed
visip_gui/dagviz/render.py
visip_gui/dagviz/style/__init__.py
visip_gui/dagviz/style/colors.py
visip_gui/dagviz/style/metro.py
visip_gui/data/__init__.py
visip_gui/data/g_action_data_model.py
visip_gui/data/tree_item.py
visip_gui/data/tree_model.py
visip_gui/dialogs/__init__.py
visip_gui/dialogs/get_text.py
visip_gui/dialogs/import_module.py
visip_gui/graphical_items/__init__.py
visip_gui/graphical_items/action_for_subactions.py
visip_gui/graphical_items/g_action.py
visip_gui/graphical_items/g_action_background.py
visip_gui/graphical_items/g_action_ref.py
visip_gui/graphical_items/g_connection.py
visip_gui/graphical_items/g_input_action.py
visip_gui/graphical_items/g_output_action.py
visip_gui/graphical_items/g_port.py
visip_gui/graphical_items/g_status_mapping.py
visip_gui/graphical_items/g_tooltip_base.py
visip_gui/graphical_items/g_tooltip_item.py
visip_gui/graphical_items/g_workflow_sr_port.py
visip-0.1.0.dist-info/LICENSE
visip-0.1.0.dist-info/METADATA
visip-0.1.0.dist-info/WHEEL
visip-0.1.0.dist-info/entry_points.txt
visip-0.1.0.dist-info/top_level.txt
visip-0.1.0.dist-info/RECORD
