Metadata-Version: 2.1
Name: visip
Version: 0.1.0
Summary: Visual Simulation Programing
Home-page: https://github.com/geomop/visip
Author: Jan Brezina, Tomas Blazek
Author-email: jan.brezina@tul.cz, tomas.blazek@tul.cz
License: GPL 3.0
Platform: UNKNOWN
Classifier: License :: OSI Approved :: GNU General Public License v3 or later (GPLv3+)
Classifier: Operating System :: Unix
Classifier: Operating System :: POSIX
Classifier: Operating System :: Microsoft :: Windows
Classifier: Programming Language :: Python :: 3
Classifier: Topic :: Scientific/Engineering
Requires-Python: >=3.8
License-File: LICENSE
Requires-Dist: numpy
Requires-Dist: PyQt5
Requires-Dist: attrs
Requires-Dist: pytypes
Requires-Dist: typing-inspect
Requires-Dist: pyqtgraph
